pyformatters_afp_quality/IPTC-MediaTopic-NewsCodes.xlsx
pyformatters_afp_quality/__init__.py
pyformatters_afp_quality/afp_quality.py
pyformatters_afp_quality-0.6.162.dist-info/entry_points.txt
pyformatters_afp_quality-0.6.162.dist-info/WHEEL
pyformatters_afp_quality-0.6.162.dist-info/METADATA
pyformatters_afp_quality-0.6.162.dist-info/RECORD
